rice_price_collector/__init__.py
rice_price_collector/config.py
rice_price_collector/downloader/__init__.py
rice_price_collector/downloader/config.py
rice_price_collector/downloader/pdf_downloader.py
rice_price_collector/parser/__init__.py
rice_price_collector/parser/batch_extract.py
rice_price_collector/parser/columns.py
rice_price_collector/parser/config.py
rice_price_collector/parser/parser.py
rice_price_collector/parser/utils.py
rice_price_collector/parser/extractors/__init__.py
rice_price_collector/parser/extractors/rice.py
rice_price_collector-0.1.5.dist-info/licenses/LICENSE
tests/test_downloader.py
tests/test_parser.py
rice_price_collector-0.1.5.dist-info/METADATA
rice_price_collector-0.1.5.dist-info/WHEEL
rice_price_collector-0.1.5.dist-info/top_level.txt
rice_price_collector-0.1.5.dist-info/RECORD
