Metadata-Version: 2.4
Name: rice_price_collector
Version: 0.1.5
Summary: Collects daily rice prices from CBSL (Central Bank of Sri Lanka) reports.
Author-email: Chamodh Chiran <your.email@example.com>
License: 
Project-URL: Homepage, https://github.com/ChamoChiran/rice_price_collector
Project-URL: Repository, https://github.com/ChamoChiran/rice_price_collector
Project-URL: Issues, https://github.com/ChamoChiran/rice_price_collector/issues
Classifier: Programming Language :: Python :: 3
Classifier: License :: OSI Approved :: MIT License
Classifier: Operating System :: OS Independent
Requires-Python: >=3.10
License-File: LICENSE
Requires-Dist: aiohttp
Requires-Dist: beautifulsoup4
Requires-Dist: pdfplumber
Requires-Dist: pandas
Dynamic: license-file
